LICENSE.md
MANIFEST.in
README.md
setup.py
app/__init__.py
app/config.py
app/views.py
app/util/__init__.py
app/util/helpers.py
docs/blank.txt
py_data_converter/__init__.py
py_data_converter/common.py
py_data_converter/config.py
py_data_converter/converter_csv.py
py_data_converter/converter_openapi.py
py_data_converter/converter_pandas.py
py_data_converter/jsonparser.py
py_data_converter/util.py
py_data_converter/__pycache__/__init__.cpython-310.pyc
py_data_converter/__pycache__/common.cpython-310.pyc
py_data_converter/__pycache__/converter_csv.cpython-310.pyc
py_data_converter/__pycache__/converter_openapi.cpython-310.pyc
py_data_converter/__pycache__/converter_pandas.cpython-310.pyc
py_data_converter/__pycache__/jsonparser.cpython-310.pyc
python_data_converter.egg-info/PKG-INFO
python_data_converter.egg-info/SOURCES.txt
python_data_converter.egg-info/dependency_links.txt
python_data_converter.egg-info/not-zip-safe
python_data_converter.egg-info/top_level.txt